{
  "scheduled_date": "9/8/2017",
  "season": 1,
  "referees": [
    { "team": 3, "player": 26 },
    { "team": 2, "player": 14 }
  ],
  "completed": true,
  "schedule_id": "1_14",
  "gamestats": [
    { "team": 4, "goals": [], "fouls": 0, "team_type": "home" },
    {
      "team": 1,
      "goals": [
        { "player": 10, "minute": 12 },
        { "player": 10, "minute": 21 },
        { "player": 9, "minute": 42 }
      ],
      "mom": [{ "player": 10 }],
      "fouls": 3,
      "team_type": "away"
    }
  ]
}
